pycmp/__init__.py
pycmp/__main__.py
pycmp/ast/__init__.py
pycmp/ast/additive.py
pycmp/ast/array.py
pycmp/ast/assigment.py
pycmp/ast/comment.py
pycmp/ast/conditional_statement.py
pycmp/ast/define_clear.py
pycmp/ast/define_global.py
pycmp/ast/equality.py
pycmp/ast/error.py
pycmp/ast/finite_unit.py
pycmp/ast/function.py
pycmp/ast/iterations.py
pycmp/ast/jump_stmt.py
pycmp/ast/lhs_rhs_node.py
pycmp/ast/logic.py
pycmp/ast/multiplicative.py
pycmp/ast/node.py
pycmp/ast/relational.py
pycmp/ast/root.py
pycmp/ast/sparse.py
pycmp/ast/transpose.py
pycmp/ast/unary_expression.py
pycmp/cli/__init__.py
pycmp/cli/cli.py
pycmp/cli/handlers_check.py
pycmp/grammar/__init__.py
pycmp/grammar/cmp_tables/__init__.py
pycmp/grammar/cmp_tables/cmp_lex_tab.py
pycmp/grammar/cmp_tables/cmp_parse_tab.py
pycmp/grammar/lexer.py
pycmp/grammar/parser.py
pycmp/helpers/__init__.py
pycmp/helpers/camel_to_snake.py
pycmp/helpers/colors.py
pycmp/helpers/exceptions.py
pycmp/helpers/log.py
pycmp/helpers/server.py
pycmp/helpers/singleton.py
pycmp/traverse/__init__.py
pycmp/traverse/traverse_ast.py
pycmp-0.1.4.dist-info/LICENSE
pycmp-0.1.4.dist-info/WHEEL
pycmp-0.1.4.dist-info/METADATA
pycmp-0.1.4.dist-info/RECORD
